{"cameraMode":{"drawMode":0,"name":"Shaded","section":"Shading Mode"},"sceneLighting":true,"audioPlay":false,"sceneViewState":{"showFog":true,"showMaterialUpdate":false,"showSkybox":true,"showFlares":true,"showImageEffects":true,"showParticleSystems":true},"in2DMode":false,"pivot":{"x":-1.4055497646331788,"y":-1.299468755722046,"z":1.0934643745422364},"rotation":{"x":-0.22855494916439057,"y":0.531507670879364,"z":-0.15157797932624818,"w":-0.8014277219772339},"size":6.036222457885742,"orthographic":false}